[{"drid":1524,"name":"Raghav","ph":9587454758,"age":35,"sex":"Male","spcl":"Cardiologists","jd":"22-03-2002","nop":56},{"drid":3526,"name":"Raman","ph":9965845215,"age":26,"sex":"Male","spcl":"Dermatologists","jd":"02-12-2001","nop":15},{"drid":6985,"name":"Anita","ph":9454654811,"age":45,"sex":"Female","spcl":"Internists","jd":"15-02-2006","nop":75},{"drid":4875,"name":"Anshuman","ph":9715541251,"age":24,"sex":"Male","spcl":"Dental","jd":"31-07-2015","nop":84},{"drid":5986,"name":"Vineet","ph":9445481232,"age":43,"sex":"Male","spcl":"Hematologists","jd":"25-02-2003","nop":59},{"drid":3562,"name":"Prerna","ph":9487153215,"age":28,"sex":"Female","spcl":"psychotherapist","jd":"16-03-2003","nop":26},{"drid":1452,"name":"Alka","ph":9235785444,"age":24,"sex":"Female","spcl":"pshysiotherapist","jd":"18-05-2019","nop":35},{"drid":4785,"name":"Lovely","ph":9845413515,"age":42,"sex":"Female","spcl":"Endocrinologists","jd":"02-03-2009","nop":21},{"drid":1596,"name":"Umesh","ph":9154865448,"age":35,"sex":"Male","spcl":"Family Physicians","jd":"15-02-2016","nop":45},{"drid":3574,"name":"Ritul","ph":9784541354,"age":36,"sex":"Male","spcl":"Gastroenterologists","jd":"11-12-2019","nop":75}]